{ 
   "string" : "New bigger string", 
   "int" : 19, 
   "double" : 13.5, 
   "Objects" : { 
      "computer" : { 
         "type" : "Asus", 
         "CPU" : "Intel core i7"
      }, 
      "phone" : { 
         "type" : "Huawei", 
         "number" : "0927482938"
      }, 
      "array" : [ 
         "first", 
         "second", 
         "third", 
         "last"
      ] 

   }, 
   "new" : { 
      "Object" : { 
         "something" : { 
            "else" : { 
                  "myObject" : "empty", 
                  "another" : [ 
                     1, 
                     2, 
                     3, 
                     4, 
                     5, 
                     6
                  ] 

               }
         }
      }
   }
}
